zeroncy/__init__.py
zeroncy/controllers.py
zeroncy/exceptions.py
zeroncy/tests/__init__.py
zeroncy/tests/common.py
zeroncy/tests/test_dot_env.py
zeroncy/tests/test_json_file.py
zeroncy-1.0.dist-info/LICENSE
zeroncy-1.0.dist-info/METADATA
zeroncy-1.0.dist-info/WHEEL
zeroncy-1.0.dist-info/top_level.txt
zeroncy-1.0.dist-info/RECORD
