Metadata-Version: 2.1
Name: zeroncy
Version: 1.0
Summary: Zero dependency lib for python
Home-page: https://github.com/Lnvictor/zeroncy
Author: Victor Pereira
Author-email: vh141299@gmail.com
License: GNU 3.0
Platform: UNKNOWN
Classifier: Development Status :: 5 - Production/Stable
Classifier: Intended Audience :: Developers
Classifier: Natural Language :: English
Classifier: Operating System :: OS Independent
Classifier: Programming Language :: Python
Classifier: Programming Language :: Python :: 3
Classifier: Topic :: Software Development :: Libraries
